{"generated_at":"2026-06-28T20:47:02.830228+00:00","zones":[{"geo3":"ezt","status":"ok","aqi":10,"pm25":2.37,"noise_db":18.55,"no2":0.0,"wind_kmh":7.6,"alerts":"","trend":"Tendencias significativas: PM2.5 (µg/m³) decreciente (-0.188/h, p=0.0); PM10 (µg/m³) decreciente (-0.189/h, p=0.0); PM1 (µg/m³) decreciente (-0.178/h, p=0.0); O3 (µg/m³) creciente (+0.363/h, p=0.0007); Humedad (%) creciente (+0.096/h, p=0.0083); Ruido (dB) decreciente (-1.008/h, p=0.0).","prediction":"Proximas horas: viento moderado previsto (7.6 km/h).","confidence":{"pm25":"fiable","pm10":"fiable","no2":"no_fiable","o3":"no_fiable"},"pm25_corr_factor":1.069,"sensors":[{"mac":"E8:31:CD:C7:00:76","name":"EZTTTGOT770076","status":"ok","aqi":14,"metrics":{"pm25":{"value":3.31,"label":"PM2.5 (µg/m³)","trend":"decreciente","confidence":"fiable"},"pm10":{"value":3.31,"label":"PM10 (µg/m³)","trend":"decreciente","confidence":"fiable"},"pm1":{"value":3.14,"label":"PM1 (µg/m³)","trend":"decreciente","confidence":null}},"alerts":"","trend":"Tendencias significativas: PM2.5 (µg/m³) decreciente (-0.183/h, p=0.0); PM10 (µg/m³) decreciente (-0.185/h, p=0.0); PM1 (µg/m³) decreciente (-0.174/h, p=0.0).","prediction":"Proximas horas: viento moderado previsto (7.6 km/h).","data_quality_note":null,"points":2855},{"mac":"CC:BA:97:16:12:22","name":"EZTXIAOS361222","status":"ok","aqi":null,"metrics":{"no2":{"value":0.0,"label":"NO2 (µg/m³)","trend":"estable","confidence":"no_fiable"},"o3":{"value":82.1,"label":"O3 (µg/m³)","trend":"estable","confidence":"no_fiable"},"tmp":{"value":27.0,"label":"Temperatura (°C)","trend":"decreciente","confidence":null},"hum":{"value":66.0,"label":"Humedad (%)","trend":"creciente","confidence":null}},"alerts":"","trend":"Tendencias significativas: Temperatura (°C) decreciente (-0.088/h, p=0.0); Humedad (%) creciente (+0.210/h, p=0.0).","prediction":"Proximas horas: viento moderado previsto (7.6 km/h).","data_quality_note":"No fiables, excluidos de alertas (validado vs referencias): NO2 (µg/m³), O3 (µg/m³)","points":1433},{"mac":"A8:46:74:40:71:A6","name":"EZTESP32C3071A6","status":"ok","aqi":null,"metrics":{"db":{"value":10.08,"label":"Ruido (dB)","trend":"estable","confidence":null}},"alerts":"","trend":"Sin tendencias estadisticamente significativas en la ventana.","prediction":"Proximas horas: viento moderado previsto (7.6 km/h).","data_quality_note":null,"points":1387},{"mac":"CC:BA:97:15:55:32","name":"EZTXIAOS355532","status":"warning","aqi":null,"metrics":{"db":{"value":73.34,"label":"Ruido (dB)","trend":"creciente","confidence":null}},"alerts":"Ruido (dB) en 73.34 supera el umbral warning (65).","trend":"Tendencias significativas: Ruido (dB) creciente (+0.118/h, p=0.0037).","prediction":"Proximas horas: viento moderado previsto (7.6 km/h).","data_quality_note":null,"points":714},{"mac":"FC:B4:67:DE:CC:A2","name":"EZTTTGOT7ECCA2","status":"warning","aqi":61,"metrics":{"pm25":{"value":16.6,"label":"PM2.5 (µg/m³)","trend":"decreciente","confidence":"dudoso"},"pm10":{"value":17.2,"label":"PM10 (µg/m³)","trend":"decreciente","confidence":"fiable"},"pm1":{"value":15.4,"label":"PM1 (µg/m³)","trend":"decreciente","confidence":null},"tmp":{"value":21.27,"label":"Temperatura (°C)","trend":"decreciente","confidence":null},"hum":{"value":90.72,"label":"Humedad (%)","trend":"creciente","confidence":null}},"alerts":"Humedad (%) en 90.72 supera el umbral warning (80).","trend":"Tendencias significativas: PM2.5 (µg/m³) decreciente (-0.236/h, p=0.0003); PM10 (µg/m³) decreciente (-0.235/h, p=0.0002); PM1 (µg/m³) decreciente (-0.224/h, p=0.0002); Temperatura (°C) decreciente (-0.047/h, p=0.0086); Humedad (%) creciente (+0.245/h, p=0.0113).","prediction":"Proximas horas: viento moderado previsto (7.6 km/h).","data_quality_note":"Fiabilidad dudosa, usar con cautela: PM2.5 (µg/m³)","points":401},{"mac":"34:86:5D:AD:5C:FE","name":"EZTTTGOT7D5CFE","status":"warning","aqi":32,"metrics":{"pm25":{"value":7.56,"label":"PM2.5 (µg/m³)","trend":"decreciente","confidence":"fiable"},"pm10":{"value":7.89,"label":"PM10 (µg/m³)","trend":"decreciente","confidence":"fiable"},"pm1":{"value":7.0,"label":"PM1 (µg/m³)","trend":"decreciente","confidence":null},"tmp":{"value":23.47,"label":"Temperatura (°C)","trend":"estable","confidence":null},"hum":{"value":80.25,"label":"Humedad (%)","trend":"estable","confidence":null}},"alerts":"Humedad (%) en 80.25 supera el umbral warning (80).","trend":"Tendencias significativas: PM2.5 (µg/m³) decreciente (-0.382/h, p=0.0004); PM10 (µg/m³) decreciente (-0.380/h, p=0.0003); PM1 (µg/m³) decreciente (-0.388/h, p=0.0003).","prediction":"Proximas horas: viento moderado previsto (7.6 km/h).","data_quality_note":null,"points":30}]},{"geo3":"u33","status":"ok","aqi":24,"pm25":5.67,"noise_db":null,"no2":null,"wind_kmh":9.0,"alerts":"","trend":"Tendencias significativas: PM2.5 (µg/m³) creciente (+0.099/h, p=0.0); PM10 (µg/m³) creciente (+0.116/h, p=0.0001); PM1 (µg/m³) creciente (+0.088/h, p=0.0); Temperatura (°C) creciente (+0.031/h, p=0.0); Humedad (%) creciente (+0.191/h, p=0.0); Presión (hPa) decreciente (-0.085/h, p=0.0).","prediction":"Proximas horas: las particulas vienen subiendo; viento flojo previsto (4.4 km/h) favorece la acumulacion.","confidence":{"pm25":"dudoso","pm10":"dudoso","no2":null,"o3":null},"pm25_corr_factor":2.655,"sensors":[{"mac":"24:6F:28:7A:58:5E","name":"U33TTGOTDA585E","status":"ok","aqi":24,"metrics":{"pm25":{"value":5.67,"label":"PM2.5 (µg/m³)","trend":"creciente","confidence":"dudoso"},"pm10":{"value":6.33,"label":"PM10 (µg/m³)","trend":"creciente","confidence":"dudoso"},"pm1":{"value":4.92,"label":"PM1 (µg/m³)","trend":"creciente","confidence":null},"tmp":{"value":28.34,"label":"Temperatura (°C)","trend":"creciente","confidence":null},"hum":{"value":45.67,"label":"Humedad (%)","trend":"creciente","confidence":null},"prs":{"value":1013.14,"label":"Presión (hPa)","trend":"decreciente","confidence":null}},"alerts":"","trend":"Tendencias significativas: PM2.5 (µg/m³) creciente (+0.104/h, p=0.0); PM10 (µg/m³) creciente (+0.120/h, p=0.0); PM1 (µg/m³) creciente (+0.092/h, p=0.0); Temperatura (°C) creciente (+0.031/h, p=0.0); Humedad (%) creciente (+0.202/h, p=0.0); Presión (hPa) decreciente (-0.093/h, p=0.0).","prediction":"Proximas horas: las particulas vienen subiendo; viento flojo previsto (4.4 km/h) favorece la acumulacion.","data_quality_note":"Fiabilidad dudosa, usar con cautela: PM2.5 (µg/m³), PM10 (µg/m³)","points":285}]}],"meta":{"measurement":"fixed_stations_01","source":"CanAirIO"}}