{"generated_at":"2026-07-07T20:22:16.100515+00:00","zones":[{"geo3":"ezt","status":"ok","aqi":14,"pm25":3.24,"noise_db":58.81,"no2":29.6,"wind_kmh":0.8,"alerts":"","trend":"Tendencias significativas: PM2.5 (µg/m³) creciente (+0.059/h, p=0.0); PM10 (µg/m³) creciente (+0.059/h, p=0.0); PM1 (µg/m³) creciente (+0.057/h, p=0.0); NO2 (µg/m³) decreciente (-0.050/h, p=0.0036); O3 (µg/m³) decreciente (-0.001/h, p=0.0003); Ruido (dB) creciente (+0.077/h, p=0.0002).","prediction":"Proximas horas: las particulas vienen subiendo; viento flojo previsto (5.2 km/h) favorece la acumulacion.","confidence":{"pm25":"fiable","pm10":"fiable","no2":"no_fiable","o3":"no_fiable"},"pm25_corr_factor":2.604,"sensors":[{"mac":"E8:31:CD:C7:00:76","name":"EZTTTGOT770076","status":"ok","aqi":47,"metrics":{"pm25":{"value":11.25,"label":"PM2.5 (µg/m³)","trend":"creciente","confidence":"fiable"},"pm10":{"value":11.26,"label":"PM10 (µg/m³)","trend":"creciente","confidence":"fiable"},"pm1":{"value":10.76,"label":"PM1 (µg/m³)","trend":"creciente","confidence":null}},"alerts":"","trend":"Tendencias significativas: PM2.5 (µg/m³) creciente (+0.203/h, p=0.0); PM10 (µg/m³) creciente (+0.203/h, p=0.0); PM1 (µg/m³) creciente (+0.194/h, p=0.0).","prediction":"Proximas horas: las particulas vienen subiendo; viento flojo previsto (5.2 km/h) favorece la acumulacion.","data_quality_note":null,"points":2834,"peer_check":{"pm25":"coherente","pm10":"coherente","pm1":"coherente"}},{"mac":"08:B6:1F:90:CC:4E","name":"EZTTTGOTD0CC4E","status":"ok","aqi":null,"metrics":{"no2":{"value":147.42,"label":"NO2 (µg/m³)","trend":"estable","confidence":"no_fiable"},"tmp":{"value":33.56,"label":"Temperatura (°C)","trend":"estable","confidence":null}},"alerts":"","trend":"Sin tendencias estadisticamente significativas en la ventana.","prediction":"Proximas horas: viento flojo previsto (5.2 km/h) favorece la acumulacion.","data_quality_note":"No fiables, excluidos de alertas (validado vs referencias): NO2 (µg/m³)","points":2833,"peer_check":{"tmp":"coherente"}},{"mac":"D4:D4:DA:E0:8C:9E","name":"EZTTTGOTD08C9E","status":"ok","aqi":5,"metrics":{"pm25":{"value":1.13,"label":"PM2.5 (µg/m³)","trend":"creciente","confidence":"fiable"},"pm10":{"value":1.15,"label":"PM10 (µg/m³)","trend":"creciente","confidence":"fiable"},"pm1":{"value":1.08,"label":"PM1 (µg/m³)","trend":"creciente","confidence":null},"tmp":{"value":29.15,"label":"Temperatura (°C)","trend":"estable","confidence":null},"hum":{"value":68.74,"label":"Humedad (%)","trend":"estable","confidence":null}},"alerts":"","trend":"Tendencias significativas: PM2.5 (µg/m³) creciente (+0.018/h, p=0.0001); PM10 (µg/m³) creciente (+0.018/h, p=0.0001); PM1 (µg/m³) creciente (+0.017/h, p=0.0001).","prediction":"Proximas horas: las particulas vienen subiendo; viento flojo previsto (5.2 km/h) favorece la acumulacion.","data_quality_note":null,"points":2833,"peer_check":{"tmp":"coherente","pm25":"coherente","pm10":"coherente","pm1":"coherente","hum":"coherente"}},{"mac":"CC:BA:97:15:55:32","name":"EZTXIAOS355532","status":"warning","aqi":null,"metrics":{"db":{"value":80.85,"label":"Ruido (dB)","trend":"creciente","confidence":null}},"alerts":"Ruido (dB) en 80.85 supera el umbral warning (65).","trend":"Tendencias significativas: Ruido (dB) creciente (+0.132/h, p=0.0011).","prediction":"Proximas horas: viento flojo previsto (5.2 km/h) favorece la acumulacion.","data_quality_note":null,"points":2622},{"mac":"CC:BA:97:16:12:22","name":"EZTXIAOS361222","status":"ok","aqi":null,"metrics":{"no2":{"value":0.0,"label":"NO2 (µg/m³)","trend":"decreciente","confidence":"dudoso"},"o3":{"value":55.02,"label":"O3 (µg/m³)","trend":"decreciente","confidence":"no_fiable"},"tmp":{"value":33.76,"label":"Temperatura (°C)","trend":"estable","confidence":null},"hum":{"value":44.24,"label":"Humedad (%)","trend":"creciente","confidence":null}},"alerts":"","trend":"Tendencias significativas: NO2 (µg/m³) decreciente (+0.000/h, p=0.0003); O3 (µg/m³) decreciente (+0.000/h, p=0.0274); Humedad (%) creciente (+0.071/h, p=0.0315).","prediction":"Proximas horas: viento flojo previsto (5.2 km/h) favorece la acumulacion.","data_quality_note":"No fiables, excluidos de alertas (validado vs referencias): O3 (µg/m³). Fiabilidad dudosa, usar con cautela: NO2 (µg/m³)","points":1417,"peer_check":{"tmp":"coherente","hum":"coherente"}},{"mac":"CC:BA:97:15:4B:02","name":"EZTXIAOS354B02","status":"warning","aqi":null,"metrics":{"db":{"value":69.07,"label":"Ruido (dB)","trend":"creciente","confidence":null}},"alerts":"Ruido (dB) en 69.07 supera el umbral warning (65).","trend":"Tendencias significativas: Ruido (dB) creciente (+0.080/h, p=0.0004).","prediction":"Proximas horas: viento flojo previsto (5.2 km/h) favorece la acumulacion.","data_quality_note":null,"points":1416},{"mac":"FC:B4:67:DE:CC:A2","name":"EZTTTGOT7ECCA2","status":"ok","aqi":63,"metrics":{"pm25":{"value":17.56,"label":"PM2.5 (µg/m³)","trend":"creciente","confidence":"fiable"},"pm10":{"value":18.31,"label":"PM10 (µg/m³)","trend":"creciente","confidence":"fiable"},"pm1":{"value":16.19,"label":"PM1 (µg/m³)","trend":"creciente","confidence":null},"tmp":{"value":24.01,"label":"Temperatura (°C)","trend":"estable","confidence":null},"hum":{"value":73.29,"label":"Humedad (%)","trend":"estable","confidence":null}},"alerts":"","trend":"Tendencias significativas: PM2.5 (µg/m³) creciente (+0.279/h, p=0.0); PM10 (µg/m³) creciente (+0.280/h, p=0.0); PM1 (µg/m³) creciente (+0.263/h, p=0.0).","prediction":"Proximas horas: las particulas vienen subiendo; viento flojo previsto (5.2 km/h) favorece la acumulacion.","data_quality_note":null,"points":406,"peer_check":{"tmp":"coherente","pm25":"coherente","pm10":"coherente","pm1":"coherente","hum":"coherente"}},{"mac":"34:86:5D:AD:5C:FE","name":"EZTTTGOT7D5CFE","status":"ok","aqi":62,"metrics":{"pm25":{"value":17.12,"label":"PM2.5 (µg/m³)","trend":"creciente","confidence":"fiable"},"pm10":{"value":17.19,"label":"PM10 (µg/m³)","trend":"creciente","confidence":"fiable"},"pm1":{"value":16.06,"label":"PM1 (µg/m³)","trend":"creciente","confidence":null},"tmp":{"value":25.6,"label":"Temperatura (°C)","trend":"estable","confidence":null},"hum":{"value":67.1,"label":"Humedad (%)","trend":"estable","confidence":null}},"alerts":"","trend":"Tendencias significativas: PM2.5 (µg/m³) creciente (+0.255/h, p=0.0); PM10 (µg/m³) creciente (+0.255/h, p=0.0); PM1 (µg/m³) creciente (+0.248/h, p=0.0).","prediction":"Proximas horas: las particulas vienen subiendo; viento flojo previsto (5.2 km/h) favorece la acumulacion.","data_quality_note":null,"points":389,"peer_check":{"tmp":"coherente","pm25":"coherente","pm10":"coherente","pm1":"coherente","hum":"coherente"}}]},{"geo3":"u33","status":"ok","aqi":4,"pm25":0.85,"noise_db":null,"no2":null,"wind_kmh":16.9,"alerts":"","trend":"Tendencias significativas: Humedad (%) creciente (+0.048/h, p=0.0015); Presión (hPa) decreciente (-0.232/h, p=0.0).","prediction":"Proximas horas: viento medio previsto 15.2 km/h favorece la dispersion.","confidence":{"pm25":"no_fiable","pm10":"no_fiable","no2":null,"o3":null},"pm25_corr_factor":null,"sensors":[{"mac":"24:6F:28:7A:58:5E","name":"U33TTGOTDA585E","status":"ok","aqi":4,"metrics":{"pm25":{"value":0.85,"label":"PM2.5 (µg/m³)","trend":"estable","confidence":"no_fiable"},"pm10":{"value":1.0,"label":"PM10 (µg/m³)","trend":"estable","confidence":"no_fiable"},"pm1":{"value":0.7,"label":"PM1 (µg/m³)","trend":"estable","confidence":null},"tmp":{"value":24.46,"label":"Temperatura (°C)","trend":"estable","confidence":null},"hum":{"value":41.17,"label":"Humedad (%)","trend":"creciente","confidence":null},"prs":{"value":1002.51,"label":"Presión (hPa)","trend":"decreciente","confidence":null}},"alerts":"","trend":"Tendencias significativas: Humedad (%) creciente (+0.048/h, p=0.0015); Presión (hPa) decreciente (-0.232/h, p=0.0).","prediction":"Proximas horas: viento medio previsto 15.2 km/h favorece la dispersion.","data_quality_note":"No fiables, excluidos de alertas (validado vs referencias): PM2.5 (µg/m³), PM10 (µg/m³)","points":471}]}],"meta":{"measurement":"fixed_stations_01","source":"CanAirIO"}}