{"generated_at":"2026-06-29T08:47:03.030359+00:00","zones":[{"geo3":"ezt","status":"ok","aqi":12,"pm25":2.82,"noise_db":16.42,"no2":0.0,"wind_kmh":7.6,"alerts":"","trend":"Tendencias significativas: PM2.5 (µg/m³) decreciente (-0.059/h, p=0.0); PM10 (µg/m³) decreciente (-0.060/h, p=0.0); PM1 (µg/m³) decreciente (-0.055/h, p=0.0); O3 (µg/m³) decreciente (-0.069/h, p=0.0073); NH3 (µg/m³) decreciente (-0.944/h, p=0.0); Temperatura (°C) decreciente (-0.018/h, p=0.0); Humedad (%) decreciente (-0.045/h, p=0.015); Ruido (dB) decreciente (-0.117/h, p=0.01).","prediction":"Proximas horas: viento moderado previsto (13.0 km/h).","confidence":{"pm25":"fiable","pm10":"fiable","no2":"no_fiable","o3":"dudoso"},"pm25_corr_factor":null,"sensors":[{"mac":"E8:31:CD:C7:00:76","name":"EZTTTGOT770076","status":"ok","aqi":24,"metrics":{"pm25":{"value":5.67,"label":"PM2.5 (µg/m³)","trend":"decreciente","confidence":"fiable"},"pm10":{"value":5.67,"label":"PM10 (µg/m³)","trend":"decreciente","confidence":"fiable"},"pm1":{"value":5.4,"label":"PM1 (µg/m³)","trend":"decreciente","confidence":null}},"alerts":"","trend":"Tendencias significativas: PM2.5 (µg/m³) decreciente (-0.087/h, p=0.0); PM10 (µg/m³) decreciente (-0.087/h, p=0.0); PM1 (µg/m³) decreciente (-0.080/h, p=0.0).","prediction":"Proximas horas: viento moderado previsto (13.2 km/h).","data_quality_note":null,"points":2856},{"mac":"CC:BA:97:16:12:22","name":"EZTXIAOS361222","status":"ok","aqi":null,"metrics":{"no2":{"value":0.0,"label":"NO2 (µg/m³)","trend":"estable","confidence":"no_fiable"},"o3":{"value":86.39,"label":"O3 (µg/m³)","trend":"estable","confidence":"no_fiable"},"tmp":{"value":26.54,"label":"Temperatura (°C)","trend":"decreciente","confidence":null},"hum":{"value":64.45,"label":"Humedad (%)","trend":"creciente","confidence":null}},"alerts":"","trend":"Tendencias significativas: Temperatura (°C) decreciente (-0.084/h, p=0.0); Humedad (%) creciente (+0.168/h, p=0.0).","prediction":"Proximas horas: viento moderado previsto (13.2 km/h).","data_quality_note":"No fiables, excluidos de alertas (validado vs referencias): NO2 (µg/m³), O3 (µg/m³)","points":1433},{"mac":"A8:46:74:40:71:A6","name":"EZTESP32C3071A6","status":"ok","aqi":null,"metrics":{"db":{"value":0.0,"label":"Ruido (dB)","trend":"estable","confidence":null}},"alerts":"","trend":"Sin tendencias estadisticamente significativas en la ventana.","prediction":"Proximas horas: viento moderado previsto (13.2 km/h).","data_quality_note":null,"points":1387},{"mac":"CC:BA:97:15:55:32","name":"EZTXIAOS355532","status":"warning","aqi":null,"metrics":{"db":{"value":81.19,"label":"Ruido (dB)","trend":"estable","confidence":null}},"alerts":"Ruido (dB) en 81.19 supera el umbral warning (65).","trend":"Sin tendencias estadisticamente significativas en la ventana.","prediction":"Proximas horas: viento moderado previsto (13.2 km/h).","data_quality_note":null,"points":714},{"mac":"FC:B4:67:DE:CC:A2","name":"EZTTTGOT7ECCA2","status":"ok","aqi":31,"metrics":{"pm25":{"value":7.4,"label":"PM2.5 (µg/m³)","trend":"decreciente","confidence":"dudoso"},"pm10":{"value":7.4,"label":"PM10 (µg/m³)","trend":"decreciente","confidence":"dudoso"},"pm1":{"value":6.7,"label":"PM1 (µg/m³)","trend":"decreciente","confidence":null},"tmp":{"value":23.66,"label":"Temperatura (°C)","trend":"decreciente","confidence":null},"hum":{"value":77.53,"label":"Humedad (%)","trend":"estable","confidence":null}},"alerts":"","trend":"Tendencias significativas: PM2.5 (µg/m³) decreciente (-0.126/h, p=0.0279); PM10 (µg/m³) decreciente (-0.125/h, p=0.0261); PM1 (µg/m³) decreciente (-0.124/h, p=0.0305); Temperatura (°C) decreciente (-0.048/h, p=0.004).","prediction":"Proximas horas: viento moderado previsto (13.2 km/h).","data_quality_note":"Fiabilidad dudosa, usar con cautela: PM2.5 (µg/m³), PM10 (µg/m³)","points":403}]},{"geo3":"u33","status":"ok","aqi":7,"pm25":1.67,"noise_db":null,"no2":null,"wind_kmh":5.5,"alerts":"","trend":"Tendencias significativas: PM2.5 (µg/m³) decreciente (-0.039/h, p=0.0245); PM10 (µg/m³) decreciente (-0.046/h, p=0.0467); PM1 (µg/m³) decreciente (-0.033/h, p=0.0136); Temperatura (°C) creciente (+0.011/h, p=0.0437); Presión (hPa) creciente (+0.067/h, p=0.0142).","prediction":"Proximas horas: viento moderado previsto (7.1 km/h); lluvia prevista (4.0 mm) ayudara a lavar particulas.","confidence":{"pm25":"no_fiable","pm10":"no_fiable","no2":null,"o3":null},"pm25_corr_factor":null,"sensors":[{"mac":"24:6F:28:7A:58:5E","name":"U33TTGOTDA585E","status":"ok","aqi":7,"metrics":{"pm25":{"value":1.67,"label":"PM2.5 (µg/m³)","trend":"decreciente","confidence":"no_fiable"},"pm10":{"value":1.83,"label":"PM10 (µg/m³)","trend":"decreciente","confidence":"no_fiable"},"pm1":{"value":1.42,"label":"PM1 (µg/m³)","trend":"decreciente","confidence":null},"tmp":{"value":28.11,"label":"Temperatura (°C)","trend":"creciente","confidence":null},"hum":{"value":42.83,"label":"Humedad (%)","trend":"estable","confidence":null},"prs":{"value":1015.39,"label":"Presión (hPa)","trend":"creciente","confidence":null}},"alerts":"","trend":"Tendencias significativas: PM2.5 (µg/m³) decreciente (-0.032/h, p=0.0176); PM10 (µg/m³) decreciente (-0.035/h, p=0.0437); PM1 (µg/m³) decreciente (-0.027/h, p=0.0134); Temperatura (°C) creciente (+0.018/h, p=0.0); Presión (hPa) creciente (+0.062/h, p=0.0194).","prediction":"Proximas horas: viento moderado previsto (7.1 km/h); lluvia prevista (4.0 mm) ayudara a lavar particulas.","data_quality_note":"No fiables, excluidos de alertas (validado vs referencias): PM2.5 (µg/m³), PM10 (µg/m³)","points":476}]}],"meta":{"measurement":"fixed_stations_01","source":"CanAirIO"}}