{"generated_at":"2026-07-05T20:22:18.415829+00:00","zones":[{"geo3":"ezt","status":"ok","aqi":5,"pm25":1.19,"noise_db":54.83,"no2":28.75,"wind_kmh":7.1,"alerts":"","trend":"Tendencias significativas: PM2.5 (µg/m³) creciente (+0.027/h, p=0.0); PM10 (µg/m³) creciente (+0.028/h, p=0.0); PM1 (µg/m³) creciente (+0.025/h, p=0.0); NO2 (µg/m³) decreciente (-0.143/h, p=0.0); Temperatura (°C) creciente (+0.070/h, p=0.0069); Humedad (%) decreciente (-0.110/h, p=0.0409).","prediction":"Proximas horas: las particulas vienen subiendo; viento flojo previsto (3.9 km/h) favorece la acumulacion.","confidence":{"pm25":"fiable","pm10":"fiable","no2":"no_fiable","o3":"no_fiable"},"pm25_corr_factor":5.046,"sensors":[{"mac":"E8:31:CD:C7:00:76","name":"EZTTTGOT770076","status":"ok","aqi":17,"metrics":{"pm25":{"value":4.12,"label":"PM2.5 (µg/m³)","trend":"creciente","confidence":"fiable"},"pm10":{"value":4.12,"label":"PM10 (µg/m³)","trend":"creciente","confidence":"fiable"},"pm1":{"value":3.81,"label":"PM1 (µg/m³)","trend":"creciente","confidence":null}},"alerts":"","trend":"Tendencias significativas: PM2.5 (µg/m³) creciente (+0.103/h, p=0.0); PM10 (µg/m³) creciente (+0.103/h, p=0.0); PM1 (µg/m³) creciente (+0.097/h, p=0.0).","prediction":"Proximas horas: las particulas vienen subiendo; viento flojo previsto (3.9 km/h) favorece la acumulacion.","data_quality_note":null,"points":2840,"peer_check":{"pm25":"coherente","pm10":"coherente","pm1":"coherente"}},{"mac":"08:B6:1F:90:CC:4E","name":"EZTTTGOTD0CC4E","status":"ok","aqi":null,"metrics":{"no2":{"value":130.28,"label":"NO2 (µg/m³)","trend":"decreciente","confidence":"no_fiable"},"tmp":{"value":33.76,"label":"Temperatura (°C)","trend":"decreciente","confidence":null}},"alerts":"","trend":"Tendencias significativas: NO2 (µg/m³) decreciente (-0.420/h, p=0.0012); Temperatura (°C) decreciente (-0.035/h, p=0.0116).","prediction":"Proximas horas: viento flojo previsto (3.9 km/h) favorece la acumulacion.","data_quality_note":"No fiables, excluidos de alertas (validado vs referencias): NO2 (µg/m³)","points":2832,"peer_check":{"tmp":"dudoso"}},{"mac":"D4:D4:DA:E0:8C:9E","name":"EZTTTGOTD08C9E","status":"warning","aqi":1,"metrics":{"pm25":{"value":0.14,"label":"PM2.5 (µg/m³)","trend":"creciente","confidence":"fiable"},"pm10":{"value":0.14,"label":"PM10 (µg/m³)","trend":"creciente","confidence":"dudoso"},"pm1":{"value":0.13,"label":"PM1 (µg/m³)","trend":"creciente","confidence":null},"tmp":{"value":38.68,"label":"Temperatura (°C)","trend":"creciente","confidence":null},"hum":{"value":35.92,"label":"Humedad (%)","trend":"decreciente","confidence":null}},"alerts":"Temperatura (°C) en 38.68 supera el umbral warning (35).","trend":"Tendencias significativas: PM2.5 (µg/m³) creciente (+0.003/h, p=0.0055); PM10 (µg/m³) creciente (+0.003/h, p=0.0055); PM1 (µg/m³) creciente (+0.002/h, p=0.0112); Temperatura (°C) creciente (+0.217/h, p=0.024); Humedad (%) decreciente (-0.703/h, p=0.0009).","prediction":"Proximas horas: las particulas vienen subiendo; viento flojo previsto (3.9 km/h) favorece la acumulacion.","data_quality_note":"Fiabilidad dudosa, usar con cautela: PM10 (µg/m³)","points":2832,"peer_check":{"tmp":"dudoso","pm25":"coherente","pm10":"coherente","pm1":"coherente","hum":"coherente"}},{"mac":"CC:BA:97:15:55:32","name":"EZTXIAOS355532","status":"warning","aqi":null,"metrics":{"db":{"value":76.0,"label":"Ruido (dB)","trend":"estable","confidence":null}},"alerts":"Ruido (dB) en 76.0 supera el umbral warning (65).","trend":"Sin tendencias estadisticamente significativas en la ventana.","prediction":"Proximas horas: viento flojo previsto (3.9 km/h) favorece la acumulacion.","data_quality_note":null,"points":2831},{"mac":"CC:BA:97:16:12:22","name":"EZTXIAOS361222","status":"ok","aqi":null,"metrics":{"no2":{"value":26.93,"label":"NO2 (µg/m³)","trend":"decreciente","confidence":"no_fiable"},"o3":{"value":52.32,"label":"O3 (µg/m³)","trend":"estable","confidence":"dudoso"},"tmp":{"value":33.71,"label":"Temperatura (°C)","trend":"creciente","confidence":null},"hum":{"value":36.75,"label":"Humedad (%)","trend":"decreciente","confidence":null}},"alerts":"","trend":"Tendencias significativas: NO2 (µg/m³) decreciente (-0.152/h, p=0.0036); Temperatura (°C) creciente (+0.049/h, p=0.0135); Humedad (%) decreciente (-0.184/h, p=0.0).","prediction":"Proximas horas: viento flojo previsto (3.9 km/h) favorece la acumulacion.","data_quality_note":"No fiables, excluidos de alertas (validado vs referencias): NO2 (µg/m³). Fiabilidad dudosa, usar con cautela: O3 (µg/m³)","points":1417,"peer_check":{"tmp":"coherente","hum":"coherente"}},{"mac":"CC:BA:97:15:4B:02","name":"EZTXIAOS354B02","status":"warning","aqi":null,"metrics":{"db":{"value":67.69,"label":"Ruido (dB)","trend":"estable","confidence":null}},"alerts":"Ruido (dB) en 67.69 supera el umbral warning (65).","trend":"Sin tendencias estadisticamente significativas en la ventana.","prediction":"Proximas horas: viento flojo previsto (3.9 km/h) favorece la acumulacion.","data_quality_note":null,"points":1416},{"mac":"FC:B4:67:DE:CC:A2","name":"EZTTTGOT7ECCA2","status":"ok","aqi":20,"metrics":{"pm25":{"value":4.71,"label":"PM2.5 (µg/m³)","trend":"creciente","confidence":"fiable"},"pm10":{"value":4.82,"label":"PM10 (µg/m³)","trend":"creciente","confidence":"fiable"},"pm1":{"value":4.47,"label":"PM1 (µg/m³)","trend":"creciente","confidence":null},"tmp":{"value":28.56,"label":"Temperatura (°C)","trend":"estable","confidence":null},"hum":{"value":37.86,"label":"Humedad (%)","trend":"decreciente","confidence":null}},"alerts":"","trend":"Tendencias significativas: PM2.5 (µg/m³) creciente (+0.077/h, p=0.0); PM10 (µg/m³) creciente (+0.076/h, p=0.0); PM1 (µg/m³) creciente (+0.073/h, p=0.0); Humedad (%) decreciente (-0.592/h, p=0.0009).","prediction":"Proximas horas: las particulas vienen subiendo; viento flojo previsto (3.9 km/h) favorece la acumulacion.","data_quality_note":null,"points":398,"peer_check":{"tmp":"coherente","pm25":"coherente","pm10":"coherente","pm1":"coherente","hum":"coherente"}},{"mac":"34:86:5D:AD:5C:FE","name":"EZTTTGOT7D5CFE","status":"ok","aqi":39,"metrics":{"pm25":{"value":9.41,"label":"PM2.5 (µg/m³)","trend":"creciente","confidence":"fiable"},"pm10":{"value":10.06,"label":"PM10 (µg/m³)","trend":"creciente","confidence":"dudoso"},"pm1":{"value":8.53,"label":"PM1 (µg/m³)","trend":"creciente","confidence":null},"tmp":{"value":28.63,"label":"Temperatura (°C)","trend":"estable","confidence":null},"hum":{"value":42.04,"label":"Humedad (%)","trend":"estable","confidence":null}},"alerts":"","trend":"Tendencias significativas: PM2.5 (µg/m³) creciente (+0.125/h, p=0.0); PM10 (µg/m³) creciente (+0.130/h, p=0.0); PM1 (µg/m³) creciente (+0.119/h, p=0.0).","prediction":"Proximas horas: las particulas vienen subiendo; viento flojo previsto (3.9 km/h) favorece la acumulacion.","data_quality_note":"Fiabilidad dudosa, usar con cautela: PM10 (µg/m³)","points":391,"peer_check":{"tmp":"coherente","pm25":"dudoso","pm10":"dudoso","pm1":"dudoso","hum":"coherente"}}]},{"geo3":"u33","status":"ok","aqi":0,"pm25":0.05,"noise_db":null,"no2":null,"wind_kmh":12.5,"alerts":"","trend":"Tendencias significativas: PM2.5 (µg/m³) creciente (+0.010/h, p=0.0006); PM10 (µg/m³) creciente (+0.015/h, p=0.0013); PM1 (µg/m³) creciente (+0.007/h, p=0.0008); Temperatura (°C) decreciente (-0.007/h, p=0.0004); Humedad (%) creciente (+0.209/h, p=0.0); Presión (hPa) decreciente (-0.208/h, p=0.0).","prediction":"Proximas horas: las particulas vienen subiendo; viento moderado previsto (9.7 km/h).","confidence":{"pm25":"no_fiable","pm10":"no_fiable","no2":null,"o3":null},"pm25_corr_factor":null,"sensors":[{"mac":"24:6F:28:7A:58:5E","name":"U33TTGOTDA585E","status":"ok","aqi":0,"metrics":{"pm25":{"value":0.05,"label":"PM2.5 (µg/m³)","trend":"creciente","confidence":"no_fiable"},"pm10":{"value":0.05,"label":"PM10 (µg/m³)","trend":"creciente","confidence":"no_fiable"},"pm1":{"value":0.05,"label":"PM1 (µg/m³)","trend":"creciente","confidence":null},"tmp":{"value":24.17,"label":"Temperatura (°C)","trend":"decreciente","confidence":null},"hum":{"value":34.44,"label":"Humedad (%)","trend":"creciente","confidence":null},"prs":{"value":1010.5,"label":"Presión (hPa)","trend":"decreciente","confidence":null}},"alerts":"","trend":"Tendencias significativas: PM2.5 (µg/m³) creciente (+0.010/h, p=0.0006); PM10 (µg/m³) creciente (+0.015/h, p=0.0013); PM1 (µg/m³) creciente (+0.007/h, p=0.0008); Temperatura (°C) decreciente (-0.007/h, p=0.0004); Humedad (%) creciente (+0.209/h, p=0.0); Presión (hPa) decreciente (-0.208/h, p=0.0).","prediction":"Proximas horas: las particulas vienen subiendo; viento moderado previsto (9.6 km/h).","data_quality_note":"No fiables, excluidos de alertas (validado vs referencias): PM2.5 (µg/m³), PM10 (µg/m³)","points":472}]}],"meta":{"measurement":"fixed_stations_01","source":"CanAirIO"}}