{"generated_at":"2026-07-02T06:09:21.486404+00:00","zones":[{"geo3":"ezt","status":"warning","aqi":3,"pm25":0.68,"noise_db":74.07,"no2":36.99,"wind_kmh":6.5,"alerts":"Ruido (dB) en 74.07 supera el umbral warning (65).","trend":"Tendencias significativas: PM2.5 (µg/m³) decreciente (-0.010/h, p=0.0007); PM10 (µg/m³) decreciente (-0.011/h, p=0.0); PM1 (µg/m³) decreciente (-0.007/h, p=0.0028); NO2 (µg/m³) creciente (+0.851/h, p=0.0); Temperatura (°C) creciente (+0.067/h, p=0.0); Humedad (%) decreciente (-0.200/h, p=0.0001); Ruido (dB) decreciente (-0.181/h, p=0.0001).","prediction":"Proximas horas: viento moderado previsto (13.7 km/h).","confidence":{"pm25":"fiable","pm10":"fiable","no2":"no_fiable","o3":"no_fiable"},"pm25_corr_factor":6.073,"sensors":[{"mac":"08:B6:1F:90:CC:4E","name":"EZTTTGOTD0CC4E","status":"ok","aqi":null,"metrics":{"no2":{"value":161.57,"label":"NO2 (µg/m³)","trend":"estable","confidence":"no_fiable"},"tmp":{"value":32.54,"label":"Temperatura (°C)","trend":"creciente","confidence":null}},"alerts":"","trend":"Tendencias significativas: Temperatura (°C) creciente (+0.044/h, p=0.0).","prediction":"Proximas horas: viento moderado previsto (14.5 km/h).","data_quality_note":"No fiables, excluidos de alertas (validado vs referencias): NO2 (µg/m³)","points":2801},{"mac":"E8:31:CD:C7:00:76","name":"EZTTTGOT770076","status":"ok","aqi":9,"metrics":{"pm25":{"value":2.08,"label":"PM2.5 (µg/m³)","trend":"decreciente","confidence":"dudoso"},"pm10":{"value":2.09,"label":"PM10 (µg/m³)","trend":"decreciente","confidence":"dudoso"},"pm1":{"value":1.96,"label":"PM1 (µg/m³)","trend":"decreciente","confidence":null}},"alerts":"","trend":"Tendencias significativas: PM2.5 (µg/m³) decreciente (-0.015/h, p=0.0203); PM10 (µg/m³) decreciente (-0.018/h, p=0.0203); PM1 (µg/m³) decreciente (-0.012/h, p=0.0326).","prediction":"Proximas horas: viento moderado previsto (14.5 km/h).","data_quality_note":"Fiabilidad dudosa, usar con cautela: PM2.5 (µg/m³), PM10 (µg/m³)","points":2798},{"mac":"CC:BA:97:15:55:32","name":"EZTXIAOS355532","status":"warning","aqi":null,"metrics":{"db":{"value":77.81,"label":"Ruido (dB)","trend":"decreciente","confidence":null}},"alerts":"Ruido (dB) en 77.81 supera el umbral warning (65).","trend":"Tendencias significativas: Ruido (dB) decreciente (-0.072/h, p=0.0025).","prediction":"Proximas horas: viento moderado previsto (14.5 km/h).","data_quality_note":null,"points":2782},{"mac":"D4:D4:DA:E0:8C:9E","name":"EZTTTGOTD08C9E","status":"warning","aqi":1,"metrics":{"pm25":{"value":0.19,"label":"PM2.5 (µg/m³)","trend":"estable","confidence":"no_fiable"},"pm10":{"value":0.19,"label":"PM10 (µg/m³)","trend":"estable","confidence":"no_fiable"},"pm1":{"value":0.15,"label":"PM1 (µg/m³)","trend":"estable","confidence":null},"tmp":{"value":22.5,"label":"Temperatura (°C)","trend":"decreciente","confidence":null},"hum":{"value":84.27,"label":"Humedad (%)","trend":"estable","confidence":null}},"alerts":"Humedad (%) en 84.27 supera el umbral warning (80).","trend":"Tendencias significativas: Temperatura (°C) decreciente (-0.119/h, p=0.0002).","prediction":"Proximas horas: viento moderado previsto (14.5 km/h).","data_quality_note":"No fiables, excluidos de alertas (validado vs referencias): PM2.5 (µg/m³), PM10 (µg/m³)","points":2753},{"mac":"CC:BA:97:15:4B:02","name":"EZTXIAOS354B02","status":"warning","aqi":null,"metrics":{"db":{"value":66.58,"label":"Ruido (dB)","trend":"decreciente","confidence":null}},"alerts":"Ruido (dB) en 66.58 supera el umbral warning (65).","trend":"Tendencias significativas: Ruido (dB) decreciente (-0.060/h, p=0.0245).","prediction":"Proximas horas: viento moderado previsto (14.5 km/h).","data_quality_note":null,"points":1401},{"mac":"FC:B4:67:DE:CC:A2","name":"EZTTTGOT7ECCA2","status":"warning","aqi":20,"metrics":{"pm25":{"value":4.88,"label":"PM2.5 (µg/m³)","trend":"estable","confidence":"dudoso"},"pm10":{"value":6.9,"label":"PM10 (µg/m³)","trend":"estable","confidence":"no_fiable"},"pm1":{"value":4.47,"label":"PM1 (µg/m³)","trend":"estable","confidence":null},"tmp":{"value":18.16,"label":"Temperatura (°C)","trend":"decreciente","confidence":null},"hum":{"value":82.18,"label":"Humedad (%)","trend":"creciente","confidence":null}},"alerts":"Humedad (%) en 82.18 supera el umbral warning (80).","trend":"Tendencias significativas: Temperatura (°C) decreciente (-0.178/h, p=0.0); Humedad (%) creciente (+0.293/h, p=0.0172).","prediction":"Proximas horas: viento moderado previsto (14.5 km/h).","data_quality_note":"No fiables, excluidos de alertas (validado vs referencias): PM10 (µg/m³). Fiabilidad dudosa, usar con cautela: PM2.5 (µg/m³)","points":396}]},{"geo3":"u33","status":"ok","aqi":0,"pm25":0.08,"noise_db":null,"no2":null,"wind_kmh":6.6,"alerts":"","trend":"Tendencias significativas: PM2.5 (µg/m³) creciente (+0.001/h, p=0.0384); PM1 (µg/m³) creciente (+0.001/h, p=0.0174); Temperatura (°C) decreciente (-0.057/h, p=0.0); Humedad (%) decreciente (-0.112/h, p=0.0001); Presión (hPa) decreciente (-0.091/h, p=0.0002).","prediction":"Proximas horas: las particulas vienen subiendo; viento moderado previsto (13.3 km/h).","confidence":{"pm25":"dudoso","pm10":"dudoso","no2":null,"o3":null},"pm25_corr_factor":54.875,"sensors":[{"mac":"24:6F:28:7A:58:5E","name":"U33TTGOTDA585E","status":"ok","aqi":0,"metrics":{"pm25":{"value":0.08,"label":"PM2.5 (µg/m³)","trend":"creciente","confidence":"dudoso"},"pm10":{"value":0.25,"label":"PM10 (µg/m³)","trend":"estable","confidence":"dudoso"},"pm1":{"value":0.08,"label":"PM1 (µg/m³)","trend":"creciente","confidence":null},"tmp":{"value":25.68,"label":"Temperatura (°C)","trend":"decreciente","confidence":null},"hum":{"value":36.5,"label":"Humedad (%)","trend":"decreciente","confidence":null},"prs":{"value":1014.16,"label":"Presión (hPa)","trend":"decreciente","confidence":null}},"alerts":"","trend":"Tendencias significativas: PM2.5 (µg/m³) creciente (+0.001/h, p=0.0221); PM1 (µg/m³) creciente (+0.001/h, p=0.0092); Temperatura (°C) decreciente (-0.057/h, p=0.0); Humedad (%) decreciente (-0.100/h, p=0.0001); Presión (hPa) decreciente (-0.096/h, p=0.0).","prediction":"Proximas horas: las particulas vienen subiendo; viento moderado previsto (14.0 km/h).","data_quality_note":"Fiabilidad dudosa, usar con cautela: PM2.5 (µg/m³), PM10 (µg/m³)","points":470}]}],"meta":{"measurement":"fixed_stations_01","source":"CanAirIO"}}